setup.py
dsh_distributions/Binomialdistribution.py
dsh_distributions/Gaussiandistribution.py
dsh_distributions/Generaldistribution.py
dsh_distributions/__init__.py
dsh_distributions.egg-info/PKG-INFO
dsh_distributions.egg-info/SOURCES.txt
dsh_distributions.egg-info/dependency_links.txt
dsh_distributions.egg-info/not-zip-safe
dsh_distributions.egg-info/top_level.txt