Metadata-Version: 1.0
Name: dsh-distributions
Version: 0.2
Summary: Gaussian and Binomial distributions
Home-page: UNKNOWN
Author: Dilan Sarith Hewawitharana
Author-email: dshewawitharana@gmail.com
License: UNKNOWN
Platform: UNKNOWN
